NarrativeForge/__init__.py
NarrativeForge/speech_to_text.py
NarrativeForge/text_to_speech.py
NarrativeForge/text_to_video.py
tests/__init__.py
tests/test.py
NarrativeForge-0.1.7.dist-info/METADATA
NarrativeForge-0.1.7.dist-info/WHEEL
NarrativeForge-0.1.7.dist-info/entry_points.txt
NarrativeForge-0.1.7.dist-info/top_level.txt
NarrativeForge-0.1.7.dist-info/RECORD
