Metadata-Version: 2.1
Name: NarrativeForge
Version: 0.1.7
Summary: A package for adding text and ai generated voice to videos.
Home-page: https://github.com/supunnadeera/NarrativeForge
Author: supun nadeera
License: UNKNOWN
Project-URL: Source, https://github.com/supunnadeera/NarrativeForge
Platform: UNKNOWN
Classifier: Development Status :: 3 - Alpha
Classifier: Intended Audience :: Developers
Classifier: Programming Language :: Python :: 3.10
Requires-Dist: numpy
Requires-Dist: moviepy
Requires-Dist: openai ==1.10.0
Requires-Dist: click
